{
  "very_trusted": "非常に信頼されています",
  "merit_range_high": "とても活発で信頼度が高いです。その調子で続けてください！",
  "warned": "警告",
  "merit_range_mid": "何度も通報されています。ご注意ください！",
  "not_trusted": "信頼度が低い",
  "merit_range_low": "7日間、機能の利用が停止されます！",
  "TRUST_SCORE": "信頼スコア",
  "about_plus_title": "Plus会員",
  "about_plus_description": "Plus会員限定のタグです！",
  "register_now": "Plusに登録",
  "good_streak": "良い連続記録",
  "keep_going": "そのまま続けましょう！",
  "normal_streak": "通常の連続記録",
  "you_can_reach": "さらに上を目指せます！頑張ってください！",
  "try_active": "連続記録のため、もっとアクティブになりましょう",
  "-DAY STREAK": "日間ストリーク",
  "longest_streak": "最長ストリーク：",
  "error_no_connection": "システムエラー、または接続が失われました！",
  "retry": "再試行",
  "light_mode": "ライトモード",
  "dark_mode": "ダークモード",
  "search_placeholder": "検索中...",
  "about_plus": "今すぐ登録して、すべての機能を無制限で利用しましょう",
  "no_notifications": "まだ通知はありません"
}
